pyspse-0.1.1.dist-info/licenses/LICENSE
spse/__init__.py
spse/categories.json
spse/category_resolver.py
spse/cli.py
spse/config.py
spse/cookie_manager.py
spse/detail_getter.py
spse/json_getter.py
spse/summary_getter.py
pyspse-0.1.1.dist-info/METADATA
pyspse-0.1.1.dist-info/WHEEL
pyspse-0.1.1.dist-info/entry_points.txt
pyspse-0.1.1.dist-info/top_level.txt
pyspse-0.1.1.dist-info/RECORD
