Metadata-Version: 2.4
Name: pyspse
Version: 0.1.1
Summary: SPSE data scraper untuk pengadaan yang ditampilkan pada https://spse.inaproc.id/
Author-email: Bakhas Diso <bakhas@diso.my.id>
License: MIT
Project-URL: Homepage, https://github.com/B-Diso/pyspse
Project-URL: Repository, https://github.com/B-Diso/pyspse
Project-URL: Issues, https://github.com/B-Diso/pyspse/issues
Keywords: spse,lpse,pengadaan,scraper,tender
Classifier: Programming Language :: Python :: 3
Classifier: Programming Language :: Python :: 3 :: Only
Classifier: License :: OSI Approved :: MIT License
Classifier: Operating System :: OS Independent
Classifier: Intended Audience :: Developers
Classifier: Topic :: Internet :: WWW/HTTP
Requires-Python: >=3.9
License-File: LICENSE
Requires-Dist: requests>=2.32.0
Requires-Dist: beautifulsoup4>=4.12.0
Requires-Dist: brotli>=1.1.0
Dynamic: license-file
